mindyolo/__init__.py
mindyolo/version.py
mindyolo/csrc/__init__.py
mindyolo/csrc/setup.py
mindyolo/csrc/fast_coco_eval/__init__.py
mindyolo/csrc/fast_coco_eval/fast_coco_eval_api.py
mindyolo/data/__init__.py
mindyolo/data/albumentations.py
mindyolo/data/constants.py
mindyolo/data/dataset.py
mindyolo/data/loader.py
mindyolo/data/utils.py
mindyolo/models/__init__.py
mindyolo/models/initializer.py
mindyolo/models/model_factory.py
mindyolo/models/registry.py
mindyolo/models/yolov10.py
mindyolo/models/yolov11.py
mindyolo/models/yolov3.py
mindyolo/models/yolov4.py
mindyolo/models/yolov5.py
mindyolo/models/yolov7.py
mindyolo/models/yolov8.py
mindyolo/models/yolov9.py
mindyolo/models/yolox.py
mindyolo/models/heads/__init__.py
mindyolo/models/heads/yolov10_head.py
mindyolo/models/heads/yolov11_head.py
mindyolo/models/heads/yolov3_head.py
mindyolo/models/heads/yolov4_head.py
mindyolo/models/heads/yolov5_head.py
mindyolo/models/heads/yolov7_head.py
mindyolo/models/heads/yolov8_head.py
mindyolo/models/heads/yolov9_head.py
mindyolo/models/heads/yolox_head.py
mindyolo/models/layers/__init__.py
mindyolo/models/layers/activation.py
mindyolo/models/layers/bottleneck.py
mindyolo/models/layers/common.py
mindyolo/models/layers/conv.py
mindyolo/models/layers/implicit.py
mindyolo/models/layers/pool.py
mindyolo/models/layers/spp.py
mindyolo/models/layers/upsample.py
mindyolo/models/layers/utils.py
mindyolo/models/losses/__init__.py
mindyolo/models/losses/focal_loss.py
mindyolo/models/losses/iou_loss.py
mindyolo/models/losses/loss_factory.py
mindyolo/models/losses/yolov10_loss.py
mindyolo/models/losses/yolov11_loss.py
mindyolo/models/losses/yolov3_loss.py
mindyolo/models/losses/yolov4_loss.py
mindyolo/models/losses/yolov5_loss.py
mindyolo/models/losses/yolov7_loss.py
mindyolo/models/losses/yolov8_loss.py
mindyolo/models/losses/yolov9_loss.py
mindyolo/models/losses/yolox_loss.py
mindyolo/optim/__init__.py
mindyolo/optim/ema.py
mindyolo/optim/group_params.py
mindyolo/optim/optim_factory.py
mindyolo-0.5.0.dist-info/licenses/LICENSE.md
mindyolo-0.5.0.dist-info/METADATA
mindyolo-0.5.0.dist-info/WHEEL
mindyolo-0.5.0.dist-info/top_level.txt
mindyolo-0.5.0.dist-info/RECORD
