Metadata-Version: 2.4
Name: mindyolo
Version: 0.5.0
Summary: A toolbox of vision models and algorithms based on MindSpore.
Home-page: https://github.com/mindspore-lab/mindyolo
Author: MindSpore Ecosystem
Author-email: mindspore-ecosystem@example.com
License: Apache Software License 2.0
Project-URL: Sources, https://github.com/mindspore-lab/mindyolo
Project-URL: Issue Tracker, https://github.com/mindspore-lab/mindyolo/issues
Classifier: Development Status :: 2 - Pre-Alpha
Classifier: Intended Audience :: Developers
Classifier: License :: OSI Approved :: Apache Software License
Classifier: Natural Language :: English
Classifier: Programming Language :: Python :: 3
Classifier: Programming Language :: Python :: 3.7
Classifier: Programming Language :: Python :: 3.8
Classifier: Programming Language :: Python :: 3.9
Requires-Python: >=3.7
License-File: LICENSE.md
Dynamic: author
Dynamic: author-email
Dynamic: classifier
Dynamic: description
Dynamic: description-content-type
Dynamic: home-page
Dynamic: license
Dynamic: license-file
Dynamic: project-url
Dynamic: requires-python
Dynamic: summary
